paperless_asn_qr_codes/__init__.py
paperless_asn_qr_codes/avery_labels.py
paperless_asn_qr_codes/main.py
paperless_asn_qr_codes-0.3.0.dist-info/METADATA
paperless_asn_qr_codes-0.3.0.dist-info/WHEEL
paperless_asn_qr_codes-0.3.0.dist-info/entry_points.txt
paperless_asn_qr_codes-0.3.0.dist-info/licenses/LICENSE
paperless_asn_qr_codes-0.3.0.dist-info/RECORD
