Metadata-Version: 2.3
Name: paperless-asn-qr-codes
Version: 0.3.0
Summary: Code for generating paperless ASN labels with QR codes
Project-URL: Documentation, https://github.com/entropia/paperless-asn-qr-codes#readme
Project-URL: Issues, https://github.com/entropia/paperless-asn-qr-codes/issues
Project-URL: Source, https://github.com/entropia/paperless-asn-qr-codes
Author-email: Jan Christian Grünhage <jan.christian@gruenhage.xyz>, margau <dev@marvingaube.de>
License-Expression: GPL-3.0
License-File: LICENSE
Classifier: Development Status :: 4 - Beta
Classifier: Programming Language :: Python
Classifier: Programming Language :: Python :: 3.10
Classifier: Programming Language :: Python :: 3.11
Classifier: Programming Language :: Python :: 3.12
Classifier: Programming Language :: Python :: Implementation :: CPython
Classifier: Programming Language :: Python :: Implementation :: PyPy
Requires-Python: >=3.7
Requires-Dist: reportlab
Requires-Dist: reportlab-qrcode
